{
    "metadata": {
        "source": "Fletling, Rainer / Heckmann, Bernhard: Georeferenzierung historischer topografischer Karten des 19. Jahrhunderts mit dem Bezugsmeridian von Ferro. In DVW-Mitteilungen Hessen-Thüringen, Heft 1/2018, S. 2–15."
    },
    "source": {
        "ellipsoid": {
            "name": "bessel"
        },
        "pm": "ferro",
        "points": [
            [
                50.232619444,
                26.121725,
                0
            ],
            [
                50.425586111,
                25.398175,
                0
            ],
            [
                50.692080556,
                25.719652778,
                0
            ],
            [
                50.650847222,
                26.244825,
                0
            ],
            [
                50.302055556,
                26.591377778,
                0
            ],
            [
                49.99435,
                26.429952778,
                0
            ],
            [
                49.960669444,
                25.963211111,
                0
            ],
            [
                50.033083333,
                25.541305556,
                0
            ],
            [
                49.725225,
                26.300680556,
                0
            ],
            [
                50.339897222,
                25.641558333,
                0
            ],
            [
                50.510463889,
                25.872547222,
                0
            ],
            [
                50.838580556,
                25.874897222,
                0
            ],
            [
                50.645447222,
                25.321925,
                0
            ],
            [
                50.187027778,
                25.269427778,
                0
            ]
        ]
    },
    "target": {
        "ellipsoid": {
            "name": "GRS80"
        },
        "points": [
            [
                50.232037525864115,
                8.457286429320146,
                0
            ],
            [
                50.424974012126114,
                7.733828056675185,
                0
            ],
            [
                50.69143910962229,
                8.05526180623511,
                0
            ],
            [
                50.65021531705902,
                8.580364231646438,
                0
            ],
            [
                50.301466784148396,
                8.92687708117387,
                0
            ],
            [
                49.99379772423912,
                8.765474650545107,
                0
            ],
            [
                49.960120654809465,
                8.298793080452764,
                0
            ],
            [
                50.03252361335847,
                7.876944465210935,
                0
            ],
            [
                49.72470601376588,
                8.636217782480987,
                0
            ],
            [
                50.3393007917333,
                7.977180343490886,
                0
            ],
            [
                50.50984614844801,
                8.208138607405605,
                0
            ],
            [
                50.83792070599035,
                8.210483477511685,
                0
            ],
            [
                50.64480792603382,
                7.657585388463687,
                0
            ],
            [
                50.18644775356296,
                7.605100157993528,
                0
            ]
        ]
    }
}